platzky_sendmail/__init__.py
platzky_sendmail/entrypoint.py
platzky_sendmail-0.2.0.dist-info/METADATA
platzky_sendmail-0.2.0.dist-info/WHEEL
platzky_sendmail-0.2.0.dist-info/licenses/LICENSE
platzky_sendmail-0.2.0.dist-info/RECORD
