Metadata-Version: 2.4
Name: platzky_sendmail
Version: 0.2.0
Summary: 
License: MIT
License-File: LICENSE
Requires-Python: >=3.10,<4.0
Classifier: License :: OSI Approved :: MIT License
Classifier: Programming Language :: Python :: 3
Classifier: Programming Language :: Python :: 3.10
Classifier: Programming Language :: Python :: 3.11
Classifier: Programming Language :: Python :: 3.12
Classifier: Programming Language :: Python :: 3.13
Classifier: Programming Language :: Python :: 3.14
Requires-Dist: platzky (>=1.3.0,<2.0.0)
Requires-Dist: pydantic[email] (>=2.10.6,<3.0.0)
